[
  {"age": 0, "L": 1, "M": 49.8842, "S": 0.03795},
  {"age": 7, "L": 1, "M": 51.2555, "S": 0.03665},
  {"age": 14, "L": 1, "M": 52.4031, "S": 0.03557},
  {"age": 21, "L": 1, "M": 53.3679, "S": 0.03465},
  {"age": 28, "L": 1, "M": 54.1814, "S": 0.03384},
  {"age": 60, "L": 1, "M": 57.5696, "S": 0.03064},
  {"age": 91, "L": 1, "M": 61.4292, "S": 0.02835},
  {"age": 122, "L": 1, "M": 64.3895, "S": 0.02698},
  {"age": 153, "L": 1, "M": 66.7689, "S": 0.02628},
  {"age": 183, "L": 1, "M": 68.7495, "S": 0.02602},
  {"age": 214, "L": 1, "M": 70.4782, "S": 0.02607},
  {"age": 244, "L": 1, "M": 71.9698, "S": 0.02632},
  {"age": 275, "L": 1, "M": 73.2812, "S": 0.02670},
  {"age": 305, "L": 1, "M": 74.4461, "S": 0.02717},
  {"age": 335, "L": 1, "M": 75.4901, "S": 0.02769},
  {"age": 365, "L": 1, "M": 76.4339, "S": 0.02826},
  {"age": 396, "L": 1, "M": 77.2951, "S": 0.02886},
  {"age": 426, "L": 1, "M": 78.0886, "S": 0.02947},
  {"age": 456, "L": 1, "M": 78.8265, "S": 0.03009},
  {"age": 487, "L": 1, "M": 79.5184, "S": 0.03072},
  {"age": 517, "L": 1, "M": 80.1719, "S": 0.03135},
  {"age": 548, "L": 1, "M": 80.7936, "S": 0.03198},
  {"age": 578, "L": 1, "M": 81.3890, "S": 0.03261},
  {"age": 609, "L": 1, "M": 81.9631, "S": 0.03324},
  {"age": 639, "L": 1, "M": 82.5200, "S": 0.03387},
  {"age": 669, "L": 1, "M": 83.0629, "S": 0.03449},
  {"age": 730, "L": 1, "M": 84.1056, "S": 0.03574},
  {"age": 791, "L": 1, "M": 85.0955, "S": 0.03699},
  {"age": 852, "L": 1, "M": 86.0400, "S": 0.03823},
  {"age": 913, "L": 1, "M": 86.9455, "S": 0.03948},
  {"age": 974, "L": 1, "M": 87.8180, "S": 0.04072},
  {"age": 1095, "L": 1, "M": 89.4750, "S": 0.04321},
  {"age": 1217, "L": 1, "M": 91.0293, "S": 0.04570},
  {"age": 1339, "L": 1, "M": 92.4961, "S": 0.04820},
  {"age": 1461, "L": 1, "M": 93.8864, "S": 0.05069},
  {"age": 1583, "L": 1, "M": 95.2092, "S": 0.05319},
  {"age": 1704, "L": 1, "M": 96.4717, "S": 0.05568},
  {"age": 1826, "L": 1, "M": 97.6796, "S": 0.05817},
  {"age": 1856, "L": 1, "M": 97.9746, "S": 0.05887}
]
